qreactor.py
qt_reactor-0.6.1.dist-info/LICENSE
qt_reactor-0.6.1.dist-info/METADATA
qt_reactor-0.6.1.dist-info/WHEEL
qt_reactor-0.6.1.dist-info/top_level.txt
qt_reactor-0.6.1.dist-info/RECORD
