Metadata-Version: 2.1
Name: qt-reactor
Version: 0.6.1
Summary: Twisted Qt integration for Qt4, Qt5, and Qt6 using qtpy
Home-page: https://github.com/frmdstryr/qt-reactor
Author: Christopher R. Wood
Author-email: chris@leastauthority.com
License: MIT
Keywords: Qt,twisted,qtpy
Classifier: Development Status :: 5 - Production/Stable
Classifier: Environment :: X11 Applications :: Qt
Classifier: Framework :: Twisted
Classifier: Intended Audience :: Developers
Classifier: License :: OSI Approved :: MIT License
Classifier: Operating System :: OS Independent
Classifier: Programming Language :: Python
Classifier: Programming Language :: Python :: 2
Classifier: Programming Language :: Python :: 2.6
Classifier: Programming Language :: Python :: 2.7
Classifier: Programming Language :: Python :: 3
Classifier: Natural Language :: English
Classifier: Topic :: Software Development :: Libraries :: Python Modules
License-File: LICENSE
Requires-Dist: twisted
Requires-Dist: qtpy
